socon/__init__.py
socon/__main__.py
socon/conf/__init__.py
socon/conf/global_settings.py
socon/conf/basecommand_template/management/commands/basecommand_name.py-tpl
socon/conf/container_template/manage.py-tpl
socon/conf/container_template/container_name/__init__.py-tpl
socon/conf/container_template/container_name/settings.py-tpl
socon/conf/container_template/container_name/management/__init__.py-tpl
socon/conf/container_template/container_name/management/commands/__init__.py-tpl
socon/conf/container_template/projects/__init__.py-tpl
socon/conf/plugin_template/README.rst-tpl
socon/conf/plugin_template/setup.py-tpl
socon/conf/plugin_template/plugin_name/__init__.py-tpl
socon/conf/plugin_template/plugin_name/plugins.py-tpl
socon/conf/plugin_template/plugin_name/management/__init__.py-tpl
socon/conf/plugin_template/plugin_name/management/commands/__init__.py-tpl
socon/conf/project_template/__init__.py-tpl
socon/conf/project_template/projects.py-tpl
socon/conf/project_template/management/__init__.py-tpl
socon/conf/project_template/management/config.py-tpl
socon/conf/project_template/management/commands/__init__.py-tpl
socon/conf/projectcommand_template/management/commands/projectcommand_name.py-tpl
socon/core/__init__.py
socon/core/exceptions.py
socon/core/manager.py
socon/core/management/__init__.py
socon/core/management/base.py
socon/core/management/subcommand.py
socon/core/management/templates.py
socon/core/management/commands/__init__.py
socon/core/management/commands/check.py
socon/core/management/commands/createcommand.py
socon/core/management/commands/createcontainer.py
socon/core/management/commands/createplugin.py
socon/core/management/commands/createproject.py
socon/core/management/commands/initialize.py
socon/core/registry/__init__.py
socon/core/registry/base.py
socon/core/registry/config.py
socon/core/registry/core.py
socon/test/__init__.py
socon/test/utils.py
socon/utils/__init__.py
socon/utils/func.py
socon/utils/log.py
socon/utils/module_loading.py
socon-0.2.1.dist-info/AUTHORS
socon-0.2.1.dist-info/LICENSE
socon-0.2.1.dist-info/METADATA
socon-0.2.1.dist-info/WHEEL
socon-0.2.1.dist-info/entry_points.txt
socon-0.2.1.dist-info/top_level.txt
socon-0.2.1.dist-info/RECORD
