Metadata-Version: 2.1
Name: socon
Version: 0.2.1
Summary: A high-level Python framework that enables you to develop a generic, robust and reliable framework for your different projects.
Author-email: Stephane Capponi <stephane.capponi@gmail.com>
License: BSD-3-Clause
Project-URL: homepage, https://socon.readthedocs.io/en/latest/
Project-URL: repository, https://github.com/socon-dev/socon
Project-URL: changelog, https://github.com/socon-dev/socon/blob/master/docs/internals/changelog.txt
Keywords: projects,socon,scripts,commands
Classifier: Development Status :: 4 - Beta
Classifier: Intended Audience :: Developers
Classifier: License :: OSI Approved :: BSD License
Classifier: Operating System :: OS Independent
Classifier: Programming Language :: Python
Classifier: Programming Language :: Python :: 3
Classifier: Programming Language :: Python :: 3 :: Only
Classifier: Programming Language :: Python :: 3.9
Classifier: Topic :: Software Development :: Libraries :: Application Frameworks
Classifier: Topic :: Software Development :: Libraries :: Python Modules
Requires-Python: >=3.9
License-File: LICENSE
License-File: AUTHORS
